setup.cfg
setup.py
osimis_timer/__init__.py
osimis_timer/timeOut.py
osimis_timer/timer.py
osimis_timer.egg-info/PKG-INFO
osimis_timer.egg-info/SOURCES.txt
osimis_timer.egg-info/dependency_links.txt
osimis_timer.egg-info/top_level.txt