Metadata-Version: 1.0
Name: osimis-timer
Version: 0.2.3
Summary: Simple Timer/TimeOut helpers to measure elapsed time.
Home-page: https://bitbucket.org/osimis/python-osimis-timer
Author: Alain Mazy
Author-email: am@osimis.io
License: UNKNOWN
Keywords: timer,timeout
Platform: UNKNOWN
